{
  "stage": 7,
  "status": "frozen_after_integrity_checks",
  "stage_version": "v1_full_train_average_uniqueness_xgboost",
  "schema_version": "stage07_v1_full_train_average_uniqueness_xgboost",
  "notebook": "07_frozen_model_training.ipynb",
  "git_commit_sha": "a057ae0ce8f139ceffed38c81507d03ce1f55540",
  "software": {
    "timestamp_utc": "2026-07-17T22:12:46.720140+00:00",
    "python_version": "3.12.2 (tags/v3.12.2:6abddd9, Feb  6 2024, 21:26:36) [MSC v.1937 64 bit (AMD64)]",
    "platform": "Windows-10-10.0.19045-SP0",
    "numpy_version": "1.26.4",
    "pandas_version": "2.2.3"
  },
  "lineage": {
    "stage05_configuration_hash": "aa8a8973403a49c388f540b3eebacf9c5d5c93806c5fb702b0f1474ae2b2ef07",
    "stage06_code_commit_sha": "884bab26097ea28c8b5bdcce78192791a2c07fc3",
    "stage06_study_signature": "4e825015bd22",
    "stage06_selected_model": "xgboost",
    "stage06_selected_trial_number": 25
  },
  "training_population": {
    "events": 118464,
    "symbols": 499,
    "first_event_start_date": "2014-05-06 00:00:00",
    "last_event_start_date": "2021-03-14 00:00:00",
    "last_event_end_date": "2021-03-17 00:00:00",
    "positive_fraction": 0.5391764586709886,
    "training_population_sha256": "c5a87f8e995dde4c8075615da47345b09cc3d1022866e3fafe65f734752f625e"
  },
  "features": {
    "model_features": [
      "ema_3_distance",
      "ema_5_distance",
      "ema_8_distance",
      "ema_10_distance",
      "ema_12_distance",
      "ema_15_distance",
      "ema_30_distance",
      "ema_35_distance",
      "ema_40_distance",
      "ema_45_distance",
      "ema_50_distance",
      "ema_60_distance",
      "ema_200_distance",
      "rsi_14_centered",
      "macd_relative",
      "log_power_of_buy",
      "log_volume_ratio_30",
      "ho_buy_fraction",
      "ho_sell_fraction",
      "x_relative_strength_zscore",
      "y_return_zscore",
      "log_positive_rs_run_length",
      "body_ratio",
      "market_return_1",
      "market_return_5",
      "market_return_20",
      "market_volatility_20",
      "market_ema_20_distance",
      "market_ema_60_distance",
      "market_range_fraction",
      "market_close_location",
      "market_drawdown_60",
      "distance_above_confirmed_low_fraction",
      "distance_below_confirmed_high_fraction",
      "gmma_state"
    ],
    "numeric_features": [
      "ema_3_distance",
      "ema_5_distance",
      "ema_8_distance",
      "ema_10_distance",
      "ema_12_distance",
      "ema_15_distance",
      "ema_30_distance",
      "ema_35_distance",
      "ema_40_distance",
      "ema_45_distance",
      "ema_50_distance",
      "ema_60_distance",
      "ema_200_distance",
      "rsi_14_centered",
      "macd_relative",
      "log_power_of_buy",
      "log_volume_ratio_30",
      "ho_buy_fraction",
      "ho_sell_fraction",
      "x_relative_strength_zscore",
      "y_return_zscore",
      "log_positive_rs_run_length",
      "body_ratio",
      "market_return_1",
      "market_return_5",
      "market_return_20",
      "market_volatility_20",
      "market_ema_20_distance",
      "market_ema_60_distance",
      "market_range_fraction",
      "market_close_location",
      "market_drawdown_60",
      "distance_above_confirmed_low_fraction",
      "distance_below_confirmed_high_fraction"
    ],
    "categorical_features": [
      "gmma_state"
    ],
    "transformed_features": [
      "ema_3_distance",
      "ema_5_distance",
      "ema_8_distance",
      "ema_10_distance",
      "ema_12_distance",
      "ema_15_distance",
      "ema_30_distance",
      "ema_35_distance",
      "ema_40_distance",
      "ema_45_distance",
      "ema_50_distance",
      "ema_60_distance",
      "ema_200_distance",
      "rsi_14_centered",
      "macd_relative",
      "log_power_of_buy",
      "log_volume_ratio_30",
      "ho_buy_fraction",
      "ho_sell_fraction",
      "x_relative_strength_zscore",
      "y_return_zscore",
      "log_positive_rs_run_length",
      "body_ratio",
      "market_return_1",
      "market_return_5",
      "market_return_20",
      "market_volatility_20",
      "market_ema_20_distance",
      "market_ema_60_distance",
      "market_range_fraction",
      "market_close_location",
      "market_drawdown_60",
      "distance_above_confirmed_low_fraction",
      "distance_below_confirmed_high_fraction",
      "gmma_state_bearish",
      "gmma_state_bullish",
      "gmma_state_mixed"
    ]
  },
  "sample_weighting": {
    "population_id": "complete_eligible_train_candidate_population",
    "events": 118464,
    "symbols": 499,
    "minimum_raw_average_uniqueness": 0.032258064516128115,
    "mean_raw_average_uniqueness": 0.10796243335266649,
    "median_raw_average_uniqueness": 0.07106589646912244,
    "maximum_raw_average_uniqueness": 1.0000000000000029,
    "minimum_sample_weight": 0.29878971336960325,
    "mean_sample_weight": 1.0,
    "maximum_sample_weight": 9.26248111445799,
    "sum_sample_weight": 118464.0,
    "effective_sample_size": 56136.85636383889,
    "effective_sample_fraction": 0.4738727070151176,
    "minimum_event_duration_observations": 2,
    "median_event_duration_observations": 27.0,
    "maximum_event_duration_observations": 31,
    "maximum_symbol_concurrency": 31,
    "nonfinite_raw_uniqueness": 0,
    "nonfinite_sample_weight": 0,
    "nonpositive_sample_weight": 0,
    "validation_events_used": 0,
    "unseen_test_events_used": 0,
    "weight_source_scope": "complete_eligible_train_candidate_population",
    "concurrency_scope": "within_symbol",
    "normalization": "full_train_mean_one",
    "weights_sha256": "691b9222a34517808c6cd0d87fbfa7333e84c43333acdc2d90390ceef2e78bde"
  },
  "model": {
    "selected_model": "xgboost",
    "selected_trial_number": 25,
    "hyperparameters": {
      "n_estimators": 150,
      "max_depth": 2,
      "learning_rate": 0.1628546104452258,
      "min_child_weight": 2.0143619867929425,
      "subsample": 0.7405393416048935,
      "colsample_bytree": 0.7110250582730073,
      "gamma": 4.373925301972639,
      "reg_alpha": 1.1918704239785168e-06,
      "reg_lambda": 1.6546398167660827,
      "max_delta_step": 0,
      "class_weight_mode": "none"
    },
    "class_weight_mode": "none",
    "scale_pos_weight": 1.0,
    "random_seed": 1729,
    "fit_seconds": 2.291950499988161,
    "model_path": "E:\\Iran_stock_trade\\financial-ml-decision-support\\results\\models\\07_frozen_xgboost_pipeline.joblib",
    "model_size_bytes": 20237,
    "model_sha256": "62a7f3e58d53213c92f1803b19135895497ebf24b56fa472c54047d762740688",
    "probe_rows": 512,
    "reload_probability_max_abs_difference": 0.0,
    "reload_equivalence_passed": true
  },
  "probability_policy": {
    "calibration_fitted": false,
    "threshold_selected": false,
    "raw_probabilities_may_be_used_for_ranking": true,
    "raw_probabilities_must_not_be_interpreted_as_calibrated": true
  },
  "training_metrics_reported": false,
  "validation_data_used_for_fit": false,
  "unseen_test_used": false,
  "configuration_hash": "4328d8db0aa7aae6d6782d61f3fe8a15dc88aa63a522256a0899e62ad86755bb"
}