{
  "stage": 7,
  "status": "frozen_after_integrity_checks",
  "stage_version": "v2_full_train_selected_feature_set_average_uniqueness_xgboost",
  "schema_version": "stage07_v2_full_train_selected_feature_set_average_uniqueness_xgboost",
  "notebook": "07_frozen_model_training.ipynb",
  "git_commit_sha": "4a6b344fc6219e08b32586002922f390061d285e",
  "software": {
    "timestamp_utc": "2026-07-19T16:05:56.283054+00:00",
    "python_version": "3.12.2 (tags/v3.12.2:6abddd9, Feb  6 2024, 21:26:36) [MSC v.1937 64 bit (AMD64)]",
    "platform": "Windows-10-10.0.19045-SP0",
    "numpy_version": "1.26.4",
    "pandas_version": "2.2.3"
  },
  "lineage": {
    "stage05_configuration_hash": "aa8a8973403a49c388f540b3eebacf9c5d5c93806c5fb702b0f1474ae2b2ef07",
    "stage06_code_commit_sha": "9928795ae10f0a9fd64788e1880b6cacc249e855",
    "stage06_configuration_hash": "ee11c83c947bd6e2164562bed0f797beae36977fb2e31325f6848a9232427b45",
    "stage06_study_signature": "3ac1ee3f73df",
    "stage06_selected_model": "xgboost",
    "stage06_selected_feature_set": "I_full_40",
    "stage06_selected_trial_number": 10,
    "stage06_selected_false_positive": 1029,
    "stage06_selected_precision": 0.6588196286472149
  },
  "training_population": {
    "events": 118464,
    "symbols": 499,
    "first_event_start_date": "2014-05-06 00:00:00",
    "last_event_start_date": "2021-03-14 00:00:00",
    "last_event_end_date": "2021-03-17 00:00:00",
    "positive_fraction": 0.5391764586709886,
    "training_population_sha256": "f0927c675e6160a95ee732c943776ffeeb281ff320f28eaeafff5c5ee0adcf6d"
  },
  "features": {
    "selected_feature_set": "I_full_40",
    "model_features": [
      "ema_3_distance",
      "ema_5_distance",
      "ema_8_distance",
      "ema_10_distance",
      "ema_12_distance",
      "ema_15_distance",
      "ema_30_distance",
      "ema_35_distance",
      "ema_40_distance",
      "ema_45_distance",
      "ema_50_distance",
      "ema_60_distance",
      "ema_200_distance",
      "rsi_14_centered",
      "macd_relative",
      "log_power_of_buy",
      "log_volume_ratio_30",
      "ho_buy_fraction",
      "ho_sell_fraction",
      "x_relative_strength_zscore",
      "y_return_zscore",
      "log_positive_rs_run_length",
      "body_ratio",
      "market_return_1",
      "market_return_5",
      "market_return_20",
      "market_volatility_20",
      "market_ema_20_distance",
      "market_ema_60_distance",
      "market_range_fraction",
      "market_close_location",
      "market_drawdown_60",
      "distance_above_confirmed_low_fraction",
      "distance_below_confirmed_high_fraction",
      "gmma_state",
      "started_run_length",
      "market_breadth_raw",
      "market_breadth_ema30",
      "market_breadth_slope5",
      "market_breadth_regime"
    ],
    "numeric_features": [
      "ema_3_distance",
      "ema_5_distance",
      "ema_8_distance",
      "ema_10_distance",
      "ema_12_distance",
      "ema_15_distance",
      "ema_30_distance",
      "ema_35_distance",
      "ema_40_distance",
      "ema_45_distance",
      "ema_50_distance",
      "ema_60_distance",
      "ema_200_distance",
      "rsi_14_centered",
      "macd_relative",
      "log_power_of_buy",
      "log_volume_ratio_30",
      "ho_buy_fraction",
      "ho_sell_fraction",
      "x_relative_strength_zscore",
      "y_return_zscore",
      "log_positive_rs_run_length",
      "body_ratio",
      "market_return_1",
      "market_return_5",
      "market_return_20",
      "market_volatility_20",
      "market_ema_20_distance",
      "market_ema_60_distance",
      "market_range_fraction",
      "market_close_location",
      "market_drawdown_60",
      "distance_above_confirmed_low_fraction",
      "distance_below_confirmed_high_fraction",
      "started_run_length",
      "market_breadth_raw",
      "market_breadth_ema30",
      "market_breadth_slope5"
    ],
    "categorical_features": [
      "gmma_state",
      "market_breadth_regime"
    ],
    "transformed_features": [
      "ema_3_distance",
      "ema_5_distance",
      "ema_8_distance",
      "ema_10_distance",
      "ema_12_distance",
      "ema_15_distance",
      "ema_30_distance",
      "ema_35_distance",
      "ema_40_distance",
      "ema_45_distance",
      "ema_50_distance",
      "ema_60_distance",
      "ema_200_distance",
      "rsi_14_centered",
      "macd_relative",
      "log_power_of_buy",
      "log_volume_ratio_30",
      "ho_buy_fraction",
      "ho_sell_fraction",
      "x_relative_strength_zscore",
      "y_return_zscore",
      "log_positive_rs_run_length",
      "body_ratio",
      "market_return_1",
      "market_return_5",
      "market_return_20",
      "market_volatility_20",
      "market_ema_20_distance",
      "market_ema_60_distance",
      "market_range_fraction",
      "market_close_location",
      "market_drawdown_60",
      "distance_above_confirmed_low_fraction",
      "distance_below_confirmed_high_fraction",
      "started_run_length",
      "market_breadth_raw",
      "market_breadth_ema30",
      "market_breadth_slope5",
      "gmma_state_bearish",
      "gmma_state_bullish",
      "gmma_state_mixed",
      "market_breadth_regime_broad_advance",
      "market_breadth_regime_broad_decline",
      "market_breadth_regime_deterioration",
      "market_breadth_regime_recovery_negative",
      "market_breadth_regime_recovery_positive",
      "market_breadth_regime_warmup_unavailable"
    ]
  },
  "sample_weighting": {
    "population_id": "complete_eligible_train_candidate_population",
    "events": 118464,
    "symbols": 499,
    "minimum_raw_average_uniqueness": 0.032258064516128115,
    "mean_raw_average_uniqueness": 0.10796243335266649,
    "median_raw_average_uniqueness": 0.07106589646912244,
    "maximum_raw_average_uniqueness": 1.0000000000000029,
    "minimum_sample_weight": 0.29878971336960325,
    "mean_sample_weight": 1.0,
    "maximum_sample_weight": 9.26248111445799,
    "sum_sample_weight": 118464.0,
    "effective_sample_size": 56136.85636383889,
    "effective_sample_fraction": 0.4738727070151176,
    "minimum_event_duration_observations": 2,
    "median_event_duration_observations": 27.0,
    "maximum_event_duration_observations": 31,
    "maximum_symbol_concurrency": 31,
    "nonfinite_raw_uniqueness": 0,
    "nonfinite_sample_weight": 0,
    "nonpositive_sample_weight": 0,
    "validation_events_used": 0,
    "unseen_test_events_used": 0,
    "weight_source_scope": "complete_eligible_train_candidate_population",
    "concurrency_scope": "within_symbol",
    "normalization": "full_train_mean_one",
    "weights_sha256": "691b9222a34517808c6cd0d87fbfa7333e84c43333acdc2d90390ceef2e78bde"
  },
  "model": {
    "selected_model": "xgboost",
    "selected_feature_set": "I_full_40",
    "selected_trial_number": 10,
    "hyperparameters": {
      "n_estimators": 100,
      "max_depth": 8,
      "learning_rate": 0.018637302558129572,
      "min_child_weight": 3.1732600961867776,
      "subsample": 0.6914421358691342,
      "colsample_bytree": 0.5877906125992687,
      "gamma": 2.6758232429856275,
      "reg_alpha": 0.06038497631137781,
      "reg_lambda": 48.34276122213323,
      "max_delta_step": 0,
      "class_weight_mode": "fold_weighted_ratio"
    },
    "class_weight_mode": "fold_weighted_ratio",
    "scale_pos_weight": 0.7083368709378897,
    "random_seed": 1729,
    "fit_seconds": 5.441199200009578,
    "model_path": "E:\\Iran_stock_trade\\financial-ml-decision-support\\results\\models\\07_frozen_xgboost_pipeline.joblib",
    "model_size_bytes": 342391,
    "model_sha256": "73a781551cdabd6bb67f5b9c0836a8683372e46487d9aade29e6320006086c1f",
    "probe_rows": 512,
    "reload_probability_max_abs_difference": 0.0,
    "reload_equivalence_passed": true
  },
  "signal_policy_lineage": {
    "type": "daily_cross_sectional_top_fraction",
    "fraction": 0.05,
    "minimum_signals_per_date": 1,
    "probability_threshold_selected": false
  },
  "probability_policy": {
    "calibration_fitted": false,
    "threshold_selected": false,
    "raw_probabilities_may_be_used_for_ranking": true,
    "raw_probabilities_must_not_be_interpreted_as_calibrated": true
  },
  "hard_started_filter_applied": false,
  "hard_breadth_filter_applied": false,
  "training_metrics_reported": false,
  "validation_data_used_for_fit": false,
  "unseen_test_used": false,
  "configuration_hash": "91e78a910792a2e67c42ec0107fd3a4faa8276c35f9bbfc6e8de4e7334b4a7ca"
}